giant_tour_smartlog_ai_02/__init__.py
giant_tour_smartlog_ai_02/giant_tour.py
giant_tour_smartlog_ai-0.2.dist-info/LICENSE
giant_tour_smartlog_ai-0.2.dist-info/METADATA
giant_tour_smartlog_ai-0.2.dist-info/WHEEL
giant_tour_smartlog_ai-0.2.dist-info/top_level.txt
giant_tour_smartlog_ai-0.2.dist-info/RECORD
