Metadata-Version: 2.1
Name: giant-tour-smartlog-ai
Version: 0.2
Summary: A package for generating a gaint tour
Author: Mr.Hanh
License: UNKNOWN
Platform: UNKNOWN
Classifier: Programming Language :: Python :: 3
Classifier: License :: OSI Approved :: MIT License
Classifier: Operating System :: OS Independent
Requires-Python: >=3.6
License-File: LICENSE
